ocrmac/__init__.py
ocrmac/cli.py
ocrmac/ocrmac.py
ocrmac-1.0.0.dist-info/LICENSE
ocrmac-1.0.0.dist-info/METADATA
ocrmac-1.0.0.dist-info/WHEEL
ocrmac-1.0.0.dist-info/entry_points.txt
ocrmac-1.0.0.dist-info/tmp83z3pact
ocrmac-1.0.0.dist-info/top_level.txt
ocrmac-1.0.0.dist-info/RECORD
