Metadata-Version: 2.1
Name: ocrmac
Version: 1.0.0
Summary: A python wrapper to extract text from images on a mac system. Uses the vision framework from Apple.
Home-page: https://github.com/straussmaximilian/ocrmac
Author: Maximilian Strauss
Author-email: straussmaximilian@gmail.com
License: MIT license
Keywords: ocrmac
Classifier: Development Status :: 2 - Pre-Alpha
Classifier: Intended Audience :: Developers
Classifier: License :: OSI Approved :: MIT License
Classifier: Natural Language :: English
Classifier: Programming Language :: Python :: 3
Classifier: Programming Language :: Python :: 3.6
Classifier: Programming Language :: Python :: 3.7
Classifier: Programming Language :: Python :: 3.8
Requires-Python: >=3.6
License-File: LICENSE
Requires-Dist: Click>=7.0
Requires-Dist: pyobjc-framework-Vision
Requires-Dist: pillow
